[
  {
    "code": "-1",
    "description": "sample description - Montréal - Deals",
    "store_id": 160,
    "dtype": 0,
    "image_thumb_url": "sample.png",
    "dislikes": 0,
    "store_name": "Deal Store - 10 Montréal",
    "store_latitude": 0,
    "likes": 0,
    "id": 4,
    "max_usage": 0,
    "usagecount": 0,
    "ref_code": "",
    "title": "Deal 4",
    "flagcount": 0,
    "start": 1557917387,
    "image_url": "sample.png",
    "expiration": 1589539787,
    "store_address": "Montréal",
    "rep_limit": 0,
    "store_longitude": 0,
    "store_description": "sample description Montréal"
  },
  {
    "code": "-1",
    "description": "sample description - Montréal - Deals",
    "store_id": 160,
    "dtype": 0,
    "image_thumb_url": "sample.png",
    "dislikes": 0,
    "store_name": "Deal Store - 10 Montréal",
    "store_latitude": 0,
    "likes": 0,
    "id": 4,
    "max_usage": 0,
    "usagecount": 0,
    "ref_code": "",
    "title": "Deal 4",
    "flagcount": 0,
    "start": 1557917387,
    "image_url": "sample.png",
    "expiration": 1589539787,
    "store_address": "Montréal",
    "rep_limit": 0,
    "store_longitude": 0,
    "store_description": "sample description Montréal"
  }
]